lab2/lab2_server/source/adder.sv
`timescale 1ns/1ps
`default_nettype wire

/*
 * =============================================================================
 * ADDER MODULES - GATE-LEVEL IMPLEMENTATION
 * =============================================================================
 * 
 * This file contains gate-level implementations of:
 * 1. half_adder: 1-bit adder without carry input
 * 2. full_adder: 1-bit adder with carry input
 * 3. rca32: 32-bit ripple-carry adder
 * 
 * All modules use only basic gates (AND, OR, XOR) as required by specifications.
 * =============================================================================
 */

// Half Adder: Adds two 1-bit inputs, produces sum and carry
module half_adder (
    input  logic a,           // First input bit
    input  logic b,           // Second input bit
    output logic sum,         // Sum output (a XOR b)
    output logic carry        // Carry output (a AND b)
);

    // Sum = a XOR b
    xor sum_gate (sum, a, b);
    
    // Carry = a AND b  
    and carry_gate (carry, a, b);

endmodule

// Full Adder: Adds two 1-bit inputs with carry input
module full_adder (
    input  logic a,           // First input bit
    input  logic b,           // Second input bit  
    input  logic carry_in,    // Carry input from previous stage
    output logic sum,         // Sum output
    output logic carry_out,   // Carry output
    output logic generate_out, // Generate output
    output logic propagate_out // Propagate output
);

    // Internal signals for intermediate calculations
    logic a_xor_b;            // a XOR b
    logic a_and_b;            // a AND b
    logic xor_result_and_cin; // (a XOR b) AND carry_in

    // Calculate a XOR b
    xor xor_ab_gate (propagate_out, a, b);
    
    // Calculate a AND b
    and and_ab_gate (generate_out, a, b);

    // Sum = (a XOR b) XOR carry_in
    xor sum_gate (sum, propagate_out, carry_in);
    
    // Calculate (a XOR b) AND carry_in
    and and_cin_gate (xor_result_and_cin, propagate_out, carry_in);

    // Carry out = (a AND b) OR ((a XOR b) AND carry_in)
    or carry_out_gate (carry_out, generate_out, xor_result_and_cin);
    
endmodule

// 32-bit Ripple-Carry Adder
module rca32 (
    input  logic [31:0] a,        // First 32-bit input
    input  logic [31:0] b,        // Second 32-bit input
    input  logic        carry_in, // Initial carry input
    output logic [31:0] sum,      // 32-bit sum output
    output logic        carry_out,// Final carry output
    output logic        overflow  // Overflow flag for signed arithmetic
);

    // Carry chain: 33 bits to handle carry propagation
    logic [32:0] carry_chain;

    // Initialize carry chain with input carry
    assign carry_chain[0] = carry_in;

    // Generate 32 full adders in a ripple-carry configuration
    genvar i;
    generate 
        for (i = 0; i < 32; i = i + 1) begin : gen_full_adders
            full_adder fa_stage (
                .a        (a[i]),              // Input a bit i
                .b        (b[i]),              // Input b bit i  
                .carry_in (carry_chain[i]),    // Carry from previous stage
                .sum      (sum[i]),            // Sum bit i
                .carry_out(carry_chain[i+1])   // Carry to next stage
            );
        end
    endgenerate

    // Final carry output is the carry from the last stage
    assign carry_out = carry_chain[32];
    
    // Overflow detection for signed arithmetic:
    // Overflow occurs when carry into MSB differs from carry out of MSB
    xor overflow_gate (overflow, carry_chain[31], carry_chain[32]);

endmodule

lab2/lab2_server/tb/full_adder_tb.sv
/*
 * =============================================================================
 * FULL ADDER TESTBENCH
 * =============================================================================
 * 
 * FILE: full_adder_tb.sv
 * PURPOSE: Comprehensive testbench for full_adder module
 * 
 * METHODOLOGY:
 * This testbench uses brute force testing to verify all possible input
 * combinations for the full_adder module. Since it's a 1-bit adder with
 * 3 inputs (a, b, carry_in), there are 2^3 = 8 possible combinations.
 * 
 * TESTING STRATEGY:
 * 1. BRUTE FORCE EXHAUSTIVE TESTING:
 *    - Tests all 8 possible input combinations
 *    - Verifies sum and carry_out outputs against expected values
 * 
 * 2. VERIFICATION METHODOLOGY:
 *    - Expected sum = a XOR b XOR carry_in
 *    - Expected carry_out = (a AND b) OR ((a XOR b) AND carry_in)
 *    - Detailed error reporting with binary output
 * 
 * 3. TIMING AND SIMULATION:
 *    - 10ns delays between test cases for signal propagation
 *    - VCD file generation for waveform viewing
 * 
 * TOTAL TEST COVERAGE: 8 individual test cases (100% coverage)
 * =============================================================================
 */

module full_adder_tb;

    // Test signals
    logic a, b, carry_in;
    wire sum, carry_out;
    
    // Error counter
    int errors = 0;
    int total_tests = 0;
    
    // Instantiate full_adder module
    full_adder fa_inst (
        .a        (a),
        .b        (b),
        .carry_in (carry_in),
        .sum      (sum),
        .carry_out(carry_out)
    );
    
    // Test task for full_adder
    task test_full_adder(input test_a, input test_b, input test_carry_in);
        logic expected_sum, expected_carry_out;
        
        // Calculate expected values
        expected_sum = test_a ^ test_b ^ test_carry_in;
        expected_carry_out = (test_a & test_b) | ((test_a ^ test_b) & test_carry_in);
        
        #10; // Wait for propagation
        
        if (sum !== expected_sum || carry_out !== expected_carry_out) begin
            $display("ERROR: full_adder test failed at time %t", $time);
            $display("  Inputs: a=%b, b=%b, carry_in=%b", test_a, test_b, test_carry_in);
            $display("  Expected: sum=%b, carry_out=%b", expected_sum, expected_carry_out);
            $display("  Got:      sum=%b, carry_out=%b", sum, carry_out);
            errors++;
        end
        total_tests++;
    endtask
    
    // Main test sequence
    initial begin
        $display("Starting full_adder testbench...");
        $display("=====================================");
        
        // Test all 8 possible input combinations
        $display("\nTesting all input combinations...");
        
        // Test case 0: 0 + 0 + 0 = 0, carry = 0
        a = 1'b0; b = 1'b0; carry_in = 1'b0;
        test_full_adder(1'b0, 1'b0, 1'b0);
        
        // Test case 1: 0 + 0 + 1 = 1, carry = 0
        a = 1'b0; b = 1'b0; carry_in = 1'b1;
        test_full_adder(1'b0, 1'b0, 1'b1);
        
        // Test case 2: 0 + 1 + 0 = 1, carry = 0
        a = 1'b0; b = 1'b1; carry_in = 1'b0;
        test_full_adder(1'b0, 1'b1, 1'b0);
        
        // Test case 3: 0 + 1 + 1 = 0, carry = 1
        a = 1'b0; b = 1'b1; carry_in = 1'b1;
        test_full_adder(1'b0, 1'b1, 1'b1);
        
        // Test case 4: 1 + 0 + 0 = 1, carry = 0
        a = 1'b1; b = 1'b0; carry_in = 1'b0;
        test_full_adder(1'b1, 1'b0, 1'b0);
        
        // Test case 5: 1 + 0 + 1 = 0, carry = 1
        a = 1'b1; b = 1'b0; carry_in = 1'b1;
        test_full_adder(1'b1, 1'b0, 1'b1);
        
        // Test case 6: 1 + 1 + 0 = 0, carry = 1
        a = 1'b1; b = 1'b1; carry_in = 1'b0;
        test_full_adder(1'b1, 1'b1, 1'b0);
        
        // Test case 7: 1 + 1 + 1 = 1, carry = 1
        a = 1'b1; b = 1'b1; carry_in = 1'b1;
        test_full_adder(1'b1, 1'b1, 1'b1);
        
        // Print final results
        $display("\n=====================================");
        $display("Test Results Summary:");
        $display("Total tests run: %d", total_tests);
        $display("Errors: %d", errors);
        
        if (errors == 0) begin
            $display("ALL TESTS PASSED! ✓");
        end else begin
            $display("SOME TESTS FAILED! ✗");
        end
        
        $display("=====================================");
        $finish;
    end
    
    // Generate VCD file for waveform viewing
    initial begin
        $dumpfile("full_adder_tb.vcd");
        $dumpvars(0, full_adder_tb);
    end

endmodule

lab2/lab2_server/full_adder_tb.vcd
$date
   Fri Oct 10 00:31:51 2025
$end
$version
  2022.2
$end
$timescale
  1ps
$end
$scope module full_adder_tb $end
$var reg 1 ! a $end
$var reg 1 " b $end
$var reg 1 # carry_in $end
$var wire 1 $ sum $end
$var wire 1 % carry_out $end
$var reg 32 & errors [31:0] $end
$var reg 32 ' total_tests [31:0] $end
$scope module fa_inst $end
$var wire 1 ( a $end
$var wire 1 ) b $end
$var wire 1 * carry_in $end
$var reg 1 + sum $end
$var reg 1 , carry_out $end
$var reg 1 - generate_out $end
$var reg 1 . propagate_out $end
$var reg 1 / a_xor_b $end
$var reg 1 0 a_and_b $end
$var reg 1 1 xor_result_and_cin $end
$upscope $end
$scope task test_full_adder $end
$var reg 1 2 test_a $end
$var reg 1 3 test_b $end
$var reg 1 4 test_carry_in $end
$var reg 1 5 expected_sum $end
$var reg 1 6 expected_carry_out $end
$upscope $end
$upscope $end
$enddefinitions $end
#0
$dumpvars
0!
0"
0#
0$
0%
b0 &
b0 '
0(
0)
0*
0+
0,
0-
0.
x/
x0
01
02
03
04
05
06
$end
#10000
1#
1$
b1 '
1*
1+
01
14
15
#20000
1"
0#
b10 '
1)
0*
1+
0-
1.
01
13
04
#30000
1#
0$
1%
b11 '
1*
0+
1,
11
14
05
16
#40000
1!
0"
0#
1$
0%
b100 '
1(
0)
0*
1+
0,
0-
1.
01
12
03
04
15
06
#50000
1#
0$
1%
b101 '
1*
0+
1,
11
14
05
16
#60000
1"
0#
b110 '
1)
0*
0+
1,
1-
0.
01
13
04
#70000
1#
1$
b111 '
1*
1+
01
14
15
#80000
b1000 '
